setup.py
awsparameter/__init__.py
awsparameter.egg-info/PKG-INFO
awsparameter.egg-info/SOURCES.txt
awsparameter.egg-info/dependency_links.txt
awsparameter.egg-info/not-zip-safe
awsparameter.egg-info/requires.txt
awsparameter.egg-info/top_level.txt