Metadata-Version: 1.2
Name: awsparameter
Version: 1.1
Summary: use parameter in S3 with kms
Home-page: https://github.com/Nakyungwon/parameter_s3_kms
Author: Nakyungwon
Author-email: saecomaster@gmail.com
License: UNKNOWN
Keywords: s3,kms,ssm parameter
Platform: UNKNOWN
Classifier: Programming Language :: Python :: 3
Classifier: Programming Language :: Python :: 3.2
Classifier: Programming Language :: Python :: 3.3
Classifier: Programming Language :: Python :: 3.4
Classifier: Programming Language :: Python :: 3.5
Classifier: Programming Language :: Python :: 3.6
Classifier: Programming Language :: Python :: 3.7
Requires-Python: >=3
